apiazure/__init__.py
apiazure/apiazure.py
apiazure-2.2.3.dist-info/METADATA
apiazure-2.2.3.dist-info/WHEEL
apiazure-2.2.3.dist-info/top_level.txt
apiazure-2.2.3.dist-info/RECORD
