Metadata-Version: 2.4
Name: apiazure
Version: 2.2.3
Summary: Libreria para el uso de la api de azure devops
Author-email: Carlos Castillo <robocarlos10@gmail.com>
Classifier: Programming Language :: Python :: 3
Requires-Python: >=3.12
